F6Transform/__init__.py
F6Transform-0.1.0.dist-info/LICENCE
F6Transform-0.1.0.dist-info/METADATA
F6Transform-0.1.0.dist-info/WHEEL
F6Transform-0.1.0.dist-info/top_level.txt
F6Transform-0.1.0.dist-info/RECORD
