Metadata-Version: 2.1
Name: F6Transform
Version: 0.1.0
Summary: F6 Transform: A minimal library for 3D rigid transformations.
Home-page: https://github.com/iamxuxx/F6Transform
Author: Xiangxing-Xu
Author-email: iamxuxx@outlook.com
Classifier: Programming Language :: Python :: 3
Classifier: License :: OSI Approved :: MIT License
Classifier: Operating System :: OS Independent
Requires-Python: >=3.7
License-File: LICENCE
Requires-Dist: numpy
